{
    "nodes": [
        {
            "top": "100px",
            "left": "480px",
            "id": "div1",
            "classesToAdd": "jira",
            "data": {
                "title": "ID",
                "content": "Tony Lastname"
            }
        },
        {
            "top": "340px",
            "left": "220px",
            "id": "div2",
            "classesToAdd": "jira",
            "data": {
                "title": "ID-12",
                "content": "Paul Lastname"
            }
        },
        {
            "top": "100px",
            "left": "220px",
            "id": "div3",
            "classesToAdd": "jira",
            "data": {
                "title": "ID - 16",
                "content": "Fix issue with LogSentEmail"
            }
        },
        {
            "top": "220px",
            "left": "220px",
            "id": "div4",
            "classesToAdd": "jira",
            "data": {
                "title": "ID-32",
                "content": "Euni Lastname"
            }
        },
        {
            "top": "220px",
            "left": "480px",
            "id": "div5",
            "classesToAdd": "jira",
            "data": {
                "title": "ID",
                "content": "John Lastname"
            }
        },
        {
            "top": "100px",
            "left": "740px",
            "id": "div6",
            "classesToAdd": "jira",
            "data": {
                "title": "ID",
                "content": "April Lastname"
            }
        },
        {
            "top": "220px",
            "left": "740px",
            "id": "div7",
            "classesToAdd": "jira",
            "data": {
                "title": "ID",
                "content": "Val Lastname"
            }
        },
        {
            "top": "100px",
            "left": "1000px",
            "id": "div8",
            "classesToAdd": "jira",
            "data": {
                "title": "",
                "content": "Tom Lastname"
            }
        },
        {
            "top": "80px",
            "left": "200px",
            "id": "div9",
            "data": {
                "title": "",
                "content": ""
            },
            "classesToAdd": "swim-lanes",
            "width": "",
            "height": ""
        },
        {
            "top": "80px",
            "left": "460px",
            "id": "div10",
            "data": {
                "title": "",
                "content": ""
            },
            "classesToAdd": "swim-lanes",
            "width": "",
            "height": ""
        },
        {
            "top": "80px",
            "left": "720px",
            "id": "div11",
            "data": {
                "title": "",
                "content": ""
            },
            "classesToAdd": "swim-lanes",
            "width": "",
            "height": ""
        },
        {
            "top": "80px",
            "left": "980px",
            "id": "div12",
            "data": {
                "title": "",
                "content": "two"
            },
            "classesToAdd": "swim-lanes",
            "width": "",
            "height": ""
        },
        {
            "top": "40px",
            "left": "220px",
            "id": "div13",
            "data": {
                "title": "",
                "content": "In-Progress"
            },
            "classesToAdd": "swim-lane-label",
            "width": "",
            "height": ""
        },
        {
            "top": "40px",
            "left": "480px",
            "id": "div14",
            "data": {
                "title": "",
                "content": "In-Progress"
            },
            "classesToAdd": "swim-lane-label",
            "width": "",
            "height": ""
        },
        {
            "top": "40px",
            "left": "740px",
            "id": "div15",
            "data": {
                "title": "",
                "content": "Ready For Test"
            },
            "classesToAdd": "swim-lane-label",
            "width": "",
            "height": ""
        },
        {
            "top": "40px",
            "left": "1000px",
            "id": "div16",
            "data": {
                "title": "",
                "content": "Approved"
            },
            "classesToAdd": "swim-lane-label",
            "width": "",
            "height": ""
        }
    ],
    "lines": []
}